README.rst
setup.py
shanbay_api/__init__.py
shanbay_api/authentication.py
shanbay_api/exceptions.py
shanbay_api/models.py
shanbay_api/response.py
shanbay_api/status.py
shanbay_api/tests.py
shanbay_api/urls.py
shanbay_api/views.py
shanbay_api.egg-info/PKG-INFO
shanbay_api.egg-info/SOURCES.txt
shanbay_api.egg-info/dependency_links.txt
shanbay_api.egg-info/requires.txt
shanbay_api.egg-info/top_level.txt
shanbay_api/utils/__init__.py
shanbay_api/utils/tools.py