Metadata-Version: 1.1
Name: shanbay-api
Version: 1.0.3
Summary: A pip library for construct shanbay api
Home-page: http://www.shanbay.com/
Author: Li Hao
Author-email: hao.li@shanbay.com
License: MIT
Keywords: api rest_framework development
Platform: UNKNOWN
Classifier: Development Status :: 3 - Alpha
Classifier: Intended Audience :: Developers
Classifier: Topic :: Software Development :: Build Tools
Classifier: License :: OSI Approved :: MIT License
Classifier: Programming Language :: Python :: 3
Classifier: Programming Language :: Python :: 3.2
Classifier: Programming Language :: Python :: 3.3
Classifier: Programming Language :: Python :: 3.4
Classifier: Programming Language :: Python :: 3.5
